Metadata-Version: 2.1
Name: flakehell
Version: 0.9.0
Summary: Flake8 wrapper to make it nice and configurable
Project-URL: Homepage, https://github.com/life4/flakehell
Project-URL: Documentation, https://flakehell.readthedocs.io/
Author: Gram (@orsinium)
Author-email: master_fess@mail.ru
Requires-Python: >=3.5
Classifier: Development Status :: 5 - Production/Stable
Classifier: Environment :: Console
Classifier: Framework :: Flake8
Classifier: Intended Audience :: Developers
Classifier: License :: OSI Approved :: MIT License
Classifier: Programming Language :: Python :: 3.5
Classifier: Programming Language :: Python :: 3.6
Classifier: Programming Language :: Python :: 3.7
Classifier: Programming Language :: Python :: 3.8
Classifier: Programming Language :: Python :: 3
Classifier: Programming Language :: Python
Classifier: Topic :: Software Development :: Libraries :: Python Modules
Classifier: Topic :: Software Development :: Quality Assurance
Requires-Dist: alabaster; extra == "docs"
Requires-Dist: colorama
Requires-Dist: dlint; extra == "dev"
Requires-Dist: entrypoints
Requires-Dist: flake8>=3.8.0
Requires-Dist: flake8-2020; extra == "dev"
Requires-Dist: flake8-aaa; extra == "dev"
Requires-Dist: flake8-absolute-import; extra == "dev"
Requires-Dist: flake8-alfred; extra == "dev"
Requires-Dist: flake8-annotations-complexity; extra == "dev"
Requires-Dist: flake8-bandit; extra == "dev"
Requires-Dist: flake8-black; extra == "dev"
Requires-Dist: flake8-broken-line; extra == "dev"
Requires-Dist: flake8-bugbear; extra == "dev"
Requires-Dist: flake8-builtins; extra == "dev"
Requires-Dist: flake8-coding; extra == "dev"
Requires-Dist: flake8-cognitive-complexity; extra == "dev"
Requires-Dist: flake8-commas; extra == "dev"
Requires-Dist: flake8-comprehensions; extra == "dev"
Requires-Dist: flake8-debugger; extra == "dev"
Requires-Dist: flake8-django; extra == "dev"
Requires-Dist: flake8-docstrings; extra == "dev"
Requires-Dist: flake8-eradicate; extra == "dev"
Requires-Dist: flake8-executable; extra == "dev"
Requires-Dist: flake8-expression-complexity; extra == "dev"
Requires-Dist: flake8-fixme; extra == "dev"
Requires-Dist: flake8-functions; extra == "dev"
Requires-Dist: flake8-future-import; extra == "dev"
Requires-Dist: flake8-import-order; extra == "dev"
Requires-Dist: flake8-isort; extra == "dev"
Requires-Dist: flake8-logging-format; extra == "dev"
Requires-Dist: flake8-mock; extra == "dev"
Requires-Dist: flake8-mutable; extra == "dev"
Requires-Dist: flake8-mypy; extra == "dev"
Requires-Dist: flake8-pep3101; extra == "dev"
Requires-Dist: flake8-pie; extra == "dev"
Requires-Dist: flake8-print; extra == "dev"
Requires-Dist: flake8-printf-formatting; extra == "dev"
Requires-Dist: flake8-pyi; extra == "dev"
Requires-Dist: flake8-pytest; extra == "dev"
Requires-Dist: flake8-pytest-style; extra == "dev"
Requires-Dist: flake8-quotes; extra == "dev"
Requires-Dist: flake8-requirements; extra == "dev"
Requires-Dist: flake8-rst-docstrings; extra == "dev"
Requires-Dist: flake8-scrapy; extra == "dev"
Requires-Dist: flake8-spellcheck; extra == "dev"
Requires-Dist: flake8-sql; extra == "dev"
Requires-Dist: flake8-strict; extra == "dev"
Requires-Dist: flake8-string-format; extra == "dev"
Requires-Dist: flake8-tidy-imports; extra == "dev"
Requires-Dist: flake8-todo; extra == "dev"
Requires-Dist: flake8-use-fstring; extra == "dev"
Requires-Dist: flake8-variables-names; extra == "dev"
Requires-Dist: isort[pyproject]; extra == "dev"
Requires-Dist: mccabe; extra == "dev"
Requires-Dist: pandas-vet; extra == "dev"
Requires-Dist: pep8-naming; extra == "dev"
Requires-Dist: pygments
Requires-Dist: pygments-github-lexers; extra == "docs"
Requires-Dist: pylint; extra == "dev"
Requires-Dist: pytest; extra == "dev"
Requires-Dist: recommonmark; extra == "docs"
Requires-Dist: sphinx; extra == "docs"
Requires-Dist: toml
Requires-Dist: typing-extensions; extra == "dev"
Requires-Dist: urllib3
Requires-Dist: wemake-python-styleguide; extra == "dev"
Provides-Extra: dev
Provides-Extra: docs
